openworld/sdk/fraudprevention/__init__.py
openworld/sdk/fraudprevention/client.py
openworld/sdk/fraudprevention/model.py
openworld_sdk_python_fraudprevention-0.8.1.dist-info/METADATA
openworld_sdk_python_fraudprevention-0.8.1.dist-info/WHEEL
openworld_sdk_python_fraudprevention-0.8.1.dist-info/top_level.txt
openworld_sdk_python_fraudprevention-0.8.1.dist-info/RECORD
